joho/__init__.py
joho/example.py
joho/joho.py
joho-0.19.3.dist-info/METADATA
joho-0.19.3.dist-info/RECORD
joho-0.19.3.dist-info/WHEEL
joho-0.19.3.dist-info/top_level.txt
