Metadata-Version: 2.1
Name: joho
Version: 0.19.3
Summary: HTML and SVG module to create lecture materials for 情報処理及び実習 TAC101  at University of Yamanashi (山梨大学).
Home-page: UNKNOWN
Author: CHEN, Lee Chuin
Author-email: leechuin@yamanashi.ac.jp
License: MIT
Keywords: html svg joho
Platform: UNKNOWN
Classifier: Development Status :: 3 - Alpha
Classifier: Intended Audience :: Education
Classifier: Topic :: Text Processing :: Markup :: HTML
Classifier: License :: OSI Approved :: MIT License
Requires-Python: >=2
Requires-Dist: numpy
Requires-Dist: matplotlib
